potion_client/__init__.py
potion_client/auth.py
potion_client/collection.py
potion_client/converter.py
potion_client/exceptions.py
potion_client/links.py
potion_client/resource.py
potion_client/schema.py
potion_client/utils.py
turmalin-2.5.4.dist-info/LICENSE
turmalin-2.5.4.dist-info/WHEEL
turmalin-2.5.4.dist-info/METADATA
turmalin-2.5.4.dist-info/RECORD
