Metadata-Version: 2.1
Name: turmalin
Version: 2.5.4
Summary: A client for APIs written in Flask-Potion
Home-page: https://github.com/biosustain/potion-client
License: MIT
Author: Lars Schöning
Author-email: lars@lyschoening.de
Requires-Python: >=3.7,<4.0
Classifier: License :: OSI Approved :: MIT License
Classifier: Programming Language :: Python :: 3
Classifier: Programming Language :: Python :: 3.7
Requires-Dist: jsonschema (>=3.0,<4.0)
Requires-Dist: requests (>=2.5,<3.0)
Requires-Dist: six (>=1.12,<2.0)
Project-URL: Repository, https://github.com/biosustain/potion-client
